vemomoto_core/tools/__init__.py
vemomoto_core/tools/doc_utils.py
vemomoto_core/tools/hrprint.py
vemomoto_core/tools/iterext.py
vemomoto_core/tools/saveobject.py
vemomoto_core/tools/simprofile.py
vemomoto_core/tools/tee.py
vemomoto_core_tools-0.9.0a4.dist-info/LICENSE
vemomoto_core_tools-0.9.0a4.dist-info/METADATA
vemomoto_core_tools-0.9.0a4.dist-info/WHEEL
vemomoto_core_tools-0.9.0a4.dist-info/top_level.txt
vemomoto_core_tools-0.9.0a4.dist-info/RECORD
