Metadata-Version: 2.1
Name: vemomoto-core-tools
Version: 0.9.0a4
Summary: Tools simplifying iteration, printing, saving, profiling, and documenting
Home-page: https://github.com/vemomoto/vemomoto
Author: Samuel M. Fischer
License: LGPLv3
Project-URL: Bug Tracker, https://github.com/vemomoto/vemomoto/issues
Project-URL: Documentation, https://vemomoto.github.io/vemomoto_core/vemomoto_core.tools
Project-URL: Source Code, https://github.com/vemomoto/vemomoto/tree/master/vemomoto_core/vemomoto_core_tools
Keywords: documentation,print,iterate,save,profile
Platform: UNKNOWN
Classifier: License :: OSI Approved :: GNU Lesser General Public License v3 (LGPLv3)
Classifier: Development Status :: 3 - Alpha
Classifier: Intended Audience :: Developers
Requires-Python: >=3.6
Requires-Dist: dill
